{
  "optgroups": [
    {
      "label": "Tesseract",
      "options": [
        {"value": "afr", "text": "Африкаанс", "defaultSelected": true, "selected": false},
        {"value": "amh", "text": "Амхарский", "defaultSelected": false, "selected": false},
        {"value": "ara", "text": "Арабский", "defaultSelected": false, "selected": false},
        {"value": "asm", "text": "Ассамский", "defaultSelected": false, "selected": false},
        {"value": "aze", "text": "Азербайджанский (Кириллица)", "defaultSelected": true, "selected": false},
        {"value": "bel", "text": "Беларусский", "defaultSelected": false, "selected": false},
        {"value": "ben", "text": "Бенгальский", "defaultSelected": false, "selected": false},
        {"value": "bod", "text": "Тибенский", "defaultSelected": false, "selected": false},
        {"value": "bos", "text": "Боснийский", "defaultSelected": true, "selected": false},
        {"value": "bre", "text": "Бретонский", "defaultSelected": false, "selected": false},
        {"value": "bul", "text": "Болгарский", "defaultSelected": false, "selected": false},
        {"value": "cat", "text": "Каталонский", "defaultSelected": false, "selected": false},
        {"value": "ceb", "text": "Себуанский", "defaultSelected": true, "selected": false},
        {"value": "ces", "text": "Чешский", "defaultSelected": false, "selected": false},
        {"value": "chi_sim", "text": "Китайский упрощенный", "defaultSelected": false, "selected": false},
        {"value": "chi_tra", "text": "Китайский традиционный", "defaultSelected": false, "selected": false},
        {"value": "chr", "text": "Чероки", "defaultSelected": true, "selected": false},
        {"value": "cos", "text": "Корсиканский", "defaultSelected": false, "selected": false},
        {"value": "cym", "text": "Валлийский", "defaultSelected": false, "selected": false},
        {"value": "dan", "text": "Датский", "defaultSelected": false, "selected": false},
        {"value": "deu", "text": "Немецкий", "defaultSelected": true, "selected": false},
        {"value": "deu_latf", "text": "Немецкий Fraktur Latin", "defaultSelected": false, "selected": false},
        {"value": "div", "text": "Дивехи", "defaultSelected": false, "selected": false},
        {"value": "dzo", "text": "Дзонгкэ", "defaultSelected": false, "selected": false},
        {"value": "ell", "text": "Греческий, современный", "defaultSelected": true, "selected": false},
        {"value": "eng", "text": "Английский", "defaultSelected": false, "selected": false},
        {"value": "enm", "text": "Английский средневековой", "defaultSelected": false, "selected": false},
        {"value": "epo", "text": "Эсперанто", "defaultSelected": false, "selected": false},
        {"value": "equ", "text": "Модуль обнаружения математики/уравнений", "defaultSelected": true, "selected": false},
        {"value": "est", "text": "Эстонский", "defaultSelected": false, "selected": false},
        {"value": "eus", "text": "Баскский", "defaultSelected": false, "selected": false},
        {"value": "fas", "text": "Персидский", "defaultSelected": false, "selected": false},
        {"value": "fao", "text": "Фарерский", "defaultSelected": true, "selected": false},
        {"value": "fil", "text": "Филиппинский", "defaultSelected": false, "selected": false},
        {"value": "fin", "text": "Финский", "defaultSelected": false, "selected": false},
        {"value": "fra", "text": "Французский", "defaultSelected": false, "selected": false},
        {"value": "frm", "text": "Французский средневековой", "defaultSelected": true, "selected": false},
        {"value": "fry", "text": "Западно-фризский", "defaultSelected": false, "selected": false},
        {"value": "gla", "text": "Шотландский гэльский", "defaultSelected": false, "selected": false},
        {"value": "gle", "text": "Ирландский", "defaultSelected": false, "selected": false},
        {"value": "glg", "text": "Галисийский", "defaultSelected": true, "selected": false},
        {"value": "grc", "text": "Греческий, Древний", "defaultSelected": false, "selected": false},
        {"value": "guj", "text": "Гуджарати", "defaultSelected": false, "selected": false},
        {"value": "hat", "text": "Гаитянский", "defaultSelected": false, "selected": false},
        {"value": "heb", "text": "Иврит", "defaultSelected": true, "selected": false},
        {"value": "hin", "text": "Хинди", "defaultSelected": false, "selected": false},
        {"value": "fao", "text": "Фарерский", "defaultSelected": true, "selected": false},
        {"value": "fil", "text": "Филиппинский", "defaultSelected": false, "selected": false},
        {"value": "fin", "text": "Финский", "defaultSelected": false, "selected": false},
        {"value": "fra", "text": "Французский", "defaultSelected": false, "selected": false},
        {"value": "frm", "text": "Французский средневековой", "defaultSelected": true, "selected": false},
        {"value": "fry", "text": "Западно-фризский", "defaultSelected": false, "selected": false},
        {"value": "gla", "text": "Шотландский гэльский", "defaultSelected": false, "selected": false},
        {"value": "gle", "text": "Ирландский", "defaultSelected": false, "selected": false},
        {"value": "glg", "text": "Галисийский", "defaultSelected": true, "selected": false},
        {"value": "grc", "text": "Греческий, Древний", "defaultSelected": false, "selected": false},
        {"value": "guj", "text": "Гуджарати", "defaultSelected": false, "selected": false},
        {"value": "hat", "text": "Гаитянский", "defaultSelected": false, "selected": false},
        {"value": "heb", "text": "Иврит", "defaultSelected": true, "selected": false},
        {"value": "hin", "text": "Хинди", "defaultSelected": false, "selected": false},
        {"value": "hrv", "text": "Хорватский", "defaultSelected": true, "selected": false},
        {"value": "hun", "text": "Венгерский", "defaultSelected": false, "selected": false},
        {"value": "hye", "text": "Армянский", "defaultSelected": false, "selected": false},
        {"value": "iku", "text": "Инуитский", "defaultSelected": false, "selected": false},
        {"value": "ind", "text": "Индонезийский", "defaultSelected": true, "selected": false},
        {"value": "isl", "text": "Исландский", "defaultSelected": false, "selected": false},
        {"value": "ita", "text": "Итальянский", "defaultSelected": false, "selected": false},
        {"value": "ita", "text": "Итальянский, старый", "defaultSelected": false, "selected": false},
        {"value": "jav", "text": "Яванский", "defaultSelected": true, "selected": false},
        {"value": "jpn", "text": "Японский", "defaultSelected": false, "selected": false},
        {"value": "kan", "text": "Каннада", "defaultSelected": false, "selected": false},
        {"value": "kat", "text": "Грузинский", "defaultSelected": false, "selected": false},
        {"value": "kat_old", "text": "Грузинский, старый", "defaultSelected": true, "selected": false},
        {"value": "kaz", "text": "Казахский", "defaultSelected": false, "selected": false},
        {"value": "khm", "text": "Центральный кхмерский", "defaultSelected": true, "selected": false},
        {"value": "kir", "text": "Киргизский; киргизский", "defaultSelected": false, "selected": false},
        {"value": "kmr", "text": "Курдский курманджи", "defaultSelected": false, "selected": false},
        {"value": "kor", "text": "Корейский", "defaultSelected": false, "selected": false},
        {"value": "kor_vert", "text": "Корейский вертикальный", "defaultSelected": true, "selected": false},
        {"value": "lao", "text": "Лаосский", "defaultSelected": false, "selected": false},
        {"value": "lat", "text": "Латинский", "defaultSelected": false, "selected": false},
        {"value": "lav", "text": "Латышский", "defaultSelected": false, "selected": false},
        {"value": "lit", "text": "Литовский", "defaultSelected": true, "selected": false},
        {"value": "ltz", "text": "Люксембургский", "defaultSelected": false, "selected": false},
        {"value": "mal", "text": "Малаялам", "defaultSelected": false, "selected": false},
        {"value": "mar", "text": "Маратхи", "defaultSelected": false, "selected": false},
        {"value": "mkd", "text": "Македонский", "defaultSelected": true, "selected": false},
        {"value": "mlt", "text": "Мальтийский", "defaultSelected": false, "selected": false},
        {"value": "mon", "text": "Монгольский", "defaultSelected": false, "selected": false},
        {"value": "mri", "text": "Маори", "defaultSelected": false, "selected": false},
        {"value": "msa", "text": "Малайский", "defaultSelected": true, "selected": false},
        {"value": "mya", "text": "Бирманский", "defaultSelected": false, "selected": false},
        {"value": "nep", "text": "Непальский", "defaultSelected": false, "selected": false},
        {"value": "nld", "text": "Голландский; фламандский", "defaultSelected": false, "selected": false},
        {"value": "nor", "text": "Норвежский", "defaultSelected": true, "selected": false},
        {"value": "oci", "text": "Окситанский после 1500", "defaultSelected": false, "selected": false},
        {"value": "ori", "text": "Ория", "defaultSelected": false, "selected": false},
        {"value": "osd", "text": "Модуль определения ориентации и письма", "defaultSelected": false, "selected": false},
        {"value": "pan", "text": "Панджаби; Пенджаби", "defaultSelected": true, "selected": false},
        {"value": "pol", "text": "Польский", "defaultSelected": false, "selected": false},
        {"value": "por", "text": "Португальский", "defaultSelected": false, "selected": false},
        {"value": "pus", "text": "Пушто; Пашто", "defaultSelected": false, "selected": false},
        {"value": "que", "text": "Кечуа", "defaultSelected": true, "selected": false},
        {"value": "ron", "text": "Румынский; Молдавский; Молдавский", "defaultSelected": false, "selected": false},
        {"value": "rus", "text": "Русский", "defaultSelected": false, "selected": false},
        {"value": "san", "text": "Санскрит", "defaultSelected": false, "selected": false},
        {"value": "sin", "text": "Сингальский; сингальский", "defaultSelected": true, "selected": false},
        {"value": "slk", "text": "Словацкий", "defaultSelected": false, "selected": false},
        {"value": "slv", "text": "Словенский", "defaultSelected": false, "selected": false},
        {"value": "snd", "text": "Синдхи", "defaultSelected": false, "selected": false},
        {"value": "spa", "text": "Испанский; Кастильский", "defaultSelected": true, "selected": false},
        {"value": "spa_old", "text": "Испанский; Кастильский - старый", "defaultSelected": false, "selected": false},
        {"value": "sqi", "text": "Албанский", "defaultSelected": false, "selected": false},
        {"value": "srp", "text": "Сербский", "defaultSelected": false, "selected": false},
        {"value": "srp_latn", "text": "Сербско-латинский", "defaultSelected": true, "selected": false},
        {"value": "sun", "text": "Сунданский", "defaultSelected": false, "selected": false},
        {"value": "swa", "text": "Суахили", "defaultSelected": false, "selected": false},
        {"value": "swe", "text": "Шведский", "defaultSelected": false, "selected": false},
        {"value": "syr", "text": "Сирийский", "defaultSelected": true, "selected": false},
        {"value": "tam", "text": "Тамильский", "defaultSelected": false, "selected": false},
        {"value": "tat", "text": "Татарский", "defaultSelected": true, "selected": false},
        {"value": "tel", "text": "Телугу", "defaultSelected": false, "selected": false},
        {"value": "tgk", "text": "Таджикский", "defaultSelected": false, "selected": false},
        {"value": "tha", "text": "Тайский", "defaultSelected": false, "selected": false},
        {"value": "tir", "text": "Тигринья", "defaultSelected": true, "selected": false},
        {"value": "ton", "text": "Тонга", "defaultSelected": false, "selected": false},
        {"value": "tur", "text": "Турецкий", "defaultSelected": false, "selected": false},
        {"value": "uig", "text": "Уйгурский; уйгурский", "defaultSelected": false, "selected": false},
        {"value": "ukr", "text": "Украинский", "defaultSelected": true, "selected": false},
        {"value": "urd", "text": "Урду", "defaultSelected": false, "selected": false},
        {"value": "uzb", "text": "Узбекский", "defaultSelected": false, "selected": false},
        {"value": "uzb_cyrl", "text": "Узбекско-кириллица", "defaultSelected": false, "selected": false},
        {"value": "vie", "text": "Вьетнамский", "defaultSelected": true, "selected": false},
        {"value": "yid", "text": "Идиш", "defaultSelected": false, "selected": false},
        {"value": "yor", "text": "Йоруба", "defaultSelected": true, "selected": false}
      ]
    },
    {
      "label": "Easy",
      "options": [
        {"value": 555, "text": "Английский", "defaultSelected": false, "selected": false},
        {"value": 333, "text": "Французский", "defaultSelected": false, "selected": false}
      ]
    },
    {
      "label": "Paddle",
      "options": [
        {"value": 5155, "text": "Английский", "defaultSelected": false, "selected": false},
        {"value": 3323, "text": "Французский", "defaultSelected": false, "selected": false}
      ]
    }
  ]
}